odoo8_addon_partner_contact_gender-8.0.1.0.0.99.dev16-py2.7-nspkg.pth
odoo8_addon_partner_contact_gender-8.0.1.0.0.99.dev16.dist-info/METADATA
odoo8_addon_partner_contact_gender-8.0.1.0.0.99.dev16.dist-info/RECORD
odoo8_addon_partner_contact_gender-8.0.1.0.0.99.dev16.dist-info/WHEEL
odoo8_addon_partner_contact_gender-8.0.1.0.0.99.dev16.dist-info/namespace_packages.txt
odoo8_addon_partner_contact_gender-8.0.1.0.0.99.dev16.dist-info/top_level.txt
odoo_addons/partner_contact_gender/README.rst
odoo_addons/partner_contact_gender/__init__.py
odoo_addons/partner_contact_gender/__openerp__.py
odoo_addons/partner_contact_gender/hooks.py
odoo_addons/partner_contact_gender/models.py
odoo_addons/partner_contact_gender/i18n/de.po
odoo_addons/partner_contact_gender/i18n/es.po
odoo_addons/partner_contact_gender/i18n/eu.po
odoo_addons/partner_contact_gender/i18n/fi.po
odoo_addons/partner_contact_gender/i18n/fr.po
odoo_addons/partner_contact_gender/i18n/it.po
odoo_addons/partner_contact_gender/i18n/nl.po
odoo_addons/partner_contact_gender/i18n/partner_contact_gender.pot
odoo_addons/partner_contact_gender/i18n/sl.po
odoo_addons/partner_contact_gender/static/description/icon.png
odoo_addons/partner_contact_gender/static/description/icon.svg
odoo_addons/partner_contact_gender/tests/__init__.py
odoo_addons/partner_contact_gender/tests/test_partner_contact_gender.py
odoo_addons/partner_contact_gender/views/res_partner.xml
